{
  "url": "https://www.craigslist.org/about/sites",
  "config": {
    "disk_cache_enabled": true,
    "http_browser_headers_enabled": true,
    "disk_cache_stale_policy": "use-stale-when-deadline"
  },
  "inputs": {
    "html_sha256": "cd7c36620bc7284471d5d590b6f9d98b6f474cb8214a9051488d9cd4c6bc5be3",
    "html_bytes": 83367,
    "cached_status": 200
  },
  "status": "ok",
  "total_ms": 2581.233713,
  "stages_ms": {
    "fetch": 512.046362284386,
    "css": 115.0104134037195,
    "cascade": 544.04925992716,
    "box_tree": 65.00588583688494,
    "layout": 1176.106488371949,
    "paint": 169.01530317590084
  },
  "notes": "Offline fixture: tests/pages/fixtures/craigslist.org_about_sites/index.html\nRepro: timeout -k 10 600 bash scripts/cargo_agent.sh xtask page-loop --fixture craigslist.org_about_sites --chrome --overlay --inspect-dump-json",
  "accuracy": {
    "baseline": "chrome",
    "diff_pixels": 18620,
    "diff_percent": 1.9396,
    "perceptual": 0.0122,
    "perceptual_metric": "ssim_windowed_v2",
    "first_mismatch": {
      "x": 662,
      "y": 4,
      "baseline_rgba": [
        214,
        200,
        227,
        255
      ],
      "rendered_rgba": [
        255,
        255,
        255,
        255
      ]
    },
    "tolerance": 0,
    "max_diff_percent": 0.0,
    "computed_at_commit": "4c5c53b30ed923d28fe0919a238007a0a219e1c3"
  },
  "hotspot": "layout",
  "failure_stage": null,
  "timeout_stage": null,
  "last_good_commit": "8bf9e2eb25959922508216096e17d07dcc19c045",
  "last_regression_commit": "",
  "diagnostics": {
    "stats": {
      "timings": {
        "html_decode_ms": 0.049471,
        "dom_parse_ms": 19.267266000000003,
        "dom_html5ever_ms": 10.824462,
        "dom_convert_ms": 1.138801,
        "dom_shadow_attach_ms": 0.42331,
        "dom_compat_ms": 0.0,
        "dom_meta_viewport_ms": 0.009084,
        "dom_clone_ms": null,
        "dom_top_layer_ms": null,
        "css_inlining_ms": 106.757041,
        "css_inline_extract_links_ms": null,
        "css_inline_extract_embedded_urls_ms": null,
        "css_inline_stylesheet_fetch_cpu_ms": null,
        "css_inline_stylesheet_decode_cpu_ms": null,
        "css_inline_stylesheet_absolutize_cpu_ms": null,
        "css_inline_imports_cpu_ms": null,
        "css_inline_inject_ms": null,
        "css_parse_ms": 0.512314,
        "css_parse_used_codepoints_ms": 0.000602,
        "css_parse_collect_font_faces_ms": 0.5064120000000001,
        "css_parse_load_webfonts_ms": 0.003269,
        "css_parse_collect_keyframes_ms": 0.00008999999999999999,
        "cascade_ms": 544.428637,
        "box_tree_ms": 61.189896,
        "layout_ms": 840.969515,
        "text_fallback_cpu_ms": 0.0,
        "text_shape_cpu_ms": 0.0,
        "paint_build_ms": 62.091405,
        "paint_optimize_ms": 0.114483,
        "paint_rasterize_ms": 33.248515,
        "text_rasterize_cpu_ms": 21.036100999999995,
        "encode_ms": null
      },
      "memory": {
        "dom_parse": {
          "rss_start_bytes": 118222848,
          "rss_end_bytes": 118325248
        },
        "script": {},
        "css": {
          "rss_start_bytes": 118624256,
          "rss_end_bytes": 126492672
        },
        "cascade": {
          "rss_start_bytes": 126492672,
          "rss_end_bytes": 219295744
        },
        "box_tree": {
          "rss_start_bytes": 219295744,
          "rss_end_bytes": 244686848
        },
        "layout": {
          "rss_start_bytes": 244686848,
          "rss_end_bytes": 286302208
        },
        "paint": {
          "rss_start_bytes": 335298560,
          "rss_end_bytes": 341958656
        }
      },
      "counts": {
        "dom_nodes": 3890,
        "styled_nodes": 3890,
        "box_nodes": 3584,
        "fragments": 5288,
        "shaped_runs": 0,
        "font_face_size_adjust_runs": 0,
        "font_face_metric_override_runs": 0,
        "glyphs": 0,
        "color_glyph_rasters": 0,
        "shaping_cache_hits": 0,
        "shaping_cache_misses": 0,
        "shaping_cache_evictions": 0,
        "shaping_cache_entries": 0,
        "fallback_cache_hits": 0,
        "fallback_cache_misses": 0,
        "fallback_cache_glyph_evictions": 0,
        "fallback_cache_cluster_evictions": 0,
        "fallback_cache_clears": 0,
        "fallback_cache_glyph_entries": null,
        "fallback_cache_cluster_entries": null,
        "fallback_cache_glyph_capacity": null,
        "fallback_cache_cluster_capacity": null,
        "fallback_cache_shards": null,
        "last_resort_font_fallbacks": 0,
        "glyph_cache_hits": 253,
        "glyph_cache_misses": 72,
        "glyph_cache_evictions": 0,
        "glyph_cache_bytes": 20025,
        "color_glyph_cache_hits": 230,
        "color_glyph_cache_misses": 95,
        "color_glyph_cache_evictions": 0,
        "color_glyph_cache_bytes": 0
      },
      "cascade": {
        "nodes": null,
        "rule_candidates": null,
        "rule_matches": null,
        "rule_candidates_pruned": null,
        "rule_candidates_by_id": null,
        "rule_candidates_by_class": null,
        "rule_candidates_by_tag": null,
        "rule_candidates_by_attr": null,
        "rule_candidates_universal": null,
        "selector_bloom_built": null,
        "selector_bloom_time_ms": null,
        "selector_rightmost_fast_rejects": null,
        "selector_match_calls": null,
        "selector_attempts_total": null,
        "selector_attempts_after_bloom": null,
        "selector_bloom_fast_rejects": null,
        "selector_time_ms": null,
        "declaration_time_ms": null,
        "pseudo_time_ms": null,
        "has_evals": null,
        "has_cache_hits": null,
        "has_prunes": null,
        "has_bloom_prunes": null,
        "has_filter_prunes": null,
        "has_evaluated": null
      },
      "layout": {
        "intrinsic_lookups": 3695,
        "intrinsic_hits": 174,
        "intrinsic_stores": 3506,
        "block_intrinsic": 1877,
        "flex_intrinsic": 9,
        "inline_intrinsic": 0,
        "layout_parallel_work_items": 3072,
        "layout_parallel_worker_threads": 16,
        "layout_parallel_enabled": true,
        "layout_parallel_auto_activated": true,
        "table_cell_intrinsic_measurements": null,
        "table_cell_layouts": null,
        "layout_cache_lookups": 12,
        "layout_cache_hits": 1,
        "layout_cache_stores": 11,
        "layout_cache_evictions": 0,
        "layout_cache_clones": 1,
        "inline_reshape_lookups": 0,
        "inline_reshape_hits": 0,
        "inline_reshape_stores": 0,
        "flex_cache_clones": 0,
        "taffy_nodes_built": 0,
        "taffy_nodes_reused": 0,
        "taffy_style_cache_hits": 0,
        "taffy_style_cache_misses": 0,
        "taffy_flex_template_evictions": 0,
        "taffy_grid_template_evictions": 0,
        "taffy_flex_compute_cpu_ms": 444.432681,
        "taffy_flex_measure_calls": 44,
        "fragment_deep_clones": 0,
        "fragment_traversed": 0
      },
      "paint": {
        "display_items": 57,
        "optimized_items": 57,
        "culled_items": 0,
        "transparent_removed": 0,
        "noop_removed": 0,
        "merged_items": 0,
        "gradient_ms": 0.0,
        "gradient_pixels": 0,
        "clip_mask_calls": 5,
        "clip_mask_ms": 0.009067,
        "clip_mask_pixels": 4800000,
        "parallel_tasks": 0,
        "parallel_threads": 1,
        "parallel_fallback_reason": "estimated paint work below parallel threshold",
        "parallel_ms": 0.0,
        "serial_ms": 95.466254,
        "filter_cache_hits": 0,
        "filter_cache_misses": 0,
        "blur_cache_hits": 0,
        "blur_cache_misses": 0,
        "blur_tiles": 0,
        "blur_calls": 0,
        "blur_ms": 0.0,
        "blur_pixels": 0,
        "blur_bytes": 0,
        "blur_cancellations": 0
      },
      "resources": {
        "fetch_counts": {
          "Stylesheet": 3
        },
        "resource_cache_fresh_hits": 0,
        "resource_cache_stale_hits": 0,
        "resource_cache_revalidated_hits": 0,
        "resource_cache_misses": 0,
        "resource_cache_bytes": 0,
        "disk_cache_hits": 0,
        "disk_cache_misses": 0,
        "disk_cache_bytes": 0,
        "disk_cache_ms": 0.0,
        "disk_cache_lock_waits": 0,
        "disk_cache_lock_wait_ms": 0.0,
        "fetch_inflight_waits": 0,
        "fetch_inflight_wait_ms": 0.0,
        "network_fetches": 0,
        "network_fetch_bytes": 0,
        "network_fetch_ms": 0.0,
        "image_cache_hits": 0,
        "image_cache_misses": 0,
        "probe_partial_requests": 0,
        "probe_partial_bytes_total": 0,
        "probe_partial_fallback_full": 0,
        "raster_pixmap_cache_hits": 0,
        "raster_pixmap_cache_misses": 0,
        "raster_pixmap_cache_bytes": 0,
        "image_decode_ms": 0.0
      }
    }
  }
}
